django_microservice_auth/__init__.py
django_microservice_auth/auth.py
django_microservice_auth/exceptions.py
django_microservice_auth-0.0.2.dist-info/METADATA
django_microservice_auth-0.0.2.dist-info/WHEEL
django_microservice_auth-0.0.2.dist-info/top_level.txt
django_microservice_auth-0.0.2.dist-info/RECORD
