Metadata-Version: 2.1
Name: django-microservice-auth
Version: 0.0.2
Summary: Django Microservice Authentication package
Home-page: https://github.com/uwaiszaki/django_user_service_auth.git
Author: Uwais Zaki
Author-email: uwaiszaki104@gmail.com
License: unlicense
Platform: UNKNOWN
Requires-Dist: Django (>=3)
Requires-Dist: djangorestframework-jwt (==1.11.0)
